lingkar33423317/__init__.py
lingkar33423317/rumus.py
lingkar33423317-0.0.2.dist-info/LICENSE
lingkar33423317-0.0.2.dist-info/METADATA
lingkar33423317-0.0.2.dist-info/WHEEL
lingkar33423317-0.0.2.dist-info/top_level.txt
lingkar33423317-0.0.2.dist-info/RECORD
