Metadata-Version: 2.1
Name: lingkar33423317
Version: 0.0.2
Summary: Simple library to calculate lingkaran
Home-page: 
Author: nihlah
Author-email: <mutiaranihlah@gmail.com>
License: MIT
Keywords: lingkaran,luas_lingkaran,luas
Classifier: Development Status :: 1 - Planning
License-File: LICENSE
